metronomes/__init__.py
metronomes/errors.py
metronomes/metronome.py
metronomes/py.typed
metronomes-0.0.12.dist-info/LICENSE
metronomes-0.0.12.dist-info/METADATA
metronomes-0.0.12.dist-info/WHEEL
metronomes-0.0.12.dist-info/top_level.txt
metronomes-0.0.12.dist-info/RECORD
