Metadata-Version: 2.1
Name: metronomes
Version: 0.0.12
Summary: Endless tick-tock generators
Author-email: Evgeniy Blinov <zheni-b@yandex.ru>
Project-URL: Source, https://github.com/pomponchik/metronomes
Project-URL: Tracker, https://github.com/pomponchik/metronomes/issues
Keywords: metronome,task scheduling,callbacks runner
Classifier: Operating System :: OS Independent
Classifier: Operating System :: MacOS :: MacOS X
Classifier: Operating System :: Microsoft :: Windows
Classifier: Operating System :: POSIX
Classifier: Operating System :: POSIX :: Linux
Classifier: Programming Language :: Python :: 3.8
Classifier: Programming Language :: Python :: 3.9
Classifier: Programming Language :: Python :: 3.10
Classifier: Programming Language :: Python :: 3.11
Classifier: Programming Language :: Python :: 3.12
Classifier: Programming Language :: Python :: 3.13
Classifier: License :: OSI Approved :: MIT License
Classifier: Intended Audience :: Developers
Classifier: Topic :: Software Development :: Libraries
Classifier: Typing :: Typed
Requires-Python: >=3.8
License-File: LICENSE
Requires-Dist: emptylog>=0.0.9
Requires-Dist: cantok>=0.0.32
Requires-Dist: escaping>=0.0.14
Requires-Dist: locklib>=0.0.17
